LICENCE.txt
MANIFEST.in
README.md
setup.py
empylib.egg-info/PKG-INFO
empylib.egg-info/SOURCES.txt
empylib.egg-info/dependency_links.txt
empylib.egg-info/requires.txt
empylib.egg-info/top_level.txt
miescattering/__init__.py
miescattering/miescattering.py
nklib/__init__.py
nklib/nklib.py
ref_spectra/__init__.py
ref_spectra/ref_spectra.py