Metadata-Version: 2.1
Name: empylib
Version: 0.0.2
Summary: Standard python library for computational electromagnetism
Home-page: https://github.com/PanxoPanza/empylib.git
Author: Francisco V. Ramirez-Cuevas
License: MIT
Keywords: electromagnetism
Platform: UNKNOWN
Classifier: Programming Language :: Python :: 3
Classifier: License :: OSI Approved :: MIT License
Classifier: Operating System :: OS Independent
Requires-Python: >=3.6, <4
License-File: LICENCE.txt
